rest_framework_reactive/__about__.py
rest_framework_reactive/__init__.py
rest_framework_reactive/api_urls.py
rest_framework_reactive/apps.py
rest_framework_reactive/connection.py
rest_framework_reactive/consumers.py
rest_framework_reactive/decorators.py
rest_framework_reactive/exceptions.py
rest_framework_reactive/models.py
rest_framework_reactive/observer.py
rest_framework_reactive/protocol.py
rest_framework_reactive/request.py
rest_framework_reactive/routing.py
rest_framework_reactive/signals.py
rest_framework_reactive/views.py
rest_framework_reactive/management/__init__.py
rest_framework_reactive/management/commands/__init__.py
rest_framework_reactive/management/commands/clearobservers.py
rest_framework_reactive/migrations/0001_initial.py
rest_framework_reactive/migrations/0002_defer_order_constraint.py
rest_framework_reactive/migrations/0003_reduce_complexity.py
rest_framework_reactive/migrations/0004_json_field.py
rest_framework_reactive/migrations/__init__.py
djangorestframework_reactive-7.0.2.dist-info/LICENSE
djangorestframework_reactive-7.0.2.dist-info/METADATA
djangorestframework_reactive-7.0.2.dist-info/WHEEL
djangorestframework_reactive-7.0.2.dist-info/top_level.txt
djangorestframework_reactive-7.0.2.dist-info/RECORD
