Metadata-Version: 2.1
Name: djangorestframework-reactive
Version: 7.0.2
Summary: Making Django REST Framework reactive
Home-page: https://github.com/genialis/django-rest-framework-reactive
Author: Genialis, Inc.
Author-email: dev-team@genialis.com
License: Apache License (2.0)
Keywords: django-rest-framework reactive django
Platform: UNKNOWN
Classifier: Development Status :: 4 - Beta
Classifier: Environment :: Web Environment
Classifier: Framework :: Django
Classifier: Intended Audience :: Developers
Classifier: Topic :: Internet :: WWW/HTTP
Classifier: Topic :: Internet :: WWW/HTTP :: Dynamic Content
Classifier: Topic :: Internet :: WWW/HTTP :: WSGI
Classifier: Topic :: Software Development :: Libraries :: Application Frameworks
Classifier: Topic :: Software Development :: Libraries :: Python Modules
Classifier: License :: OSI Approved :: Apache Software License
Classifier: Operating System :: OS Independent
Classifier: Programming Language :: Python
Classifier: Programming Language :: Python :: 3
Classifier: Programming Language :: Python :: 3.6
Classifier: Programming Language :: Python :: 3.7
Classifier: Programming Language :: Python :: 3.8
Classifier: Programming Language :: Python :: 3.9
Classifier: Programming Language :: Python :: 3.10
Requires-Python: >=3.6, <3.11
License-File: LICENSE
Requires-Dist: Django (~=3.2.12)
Requires-Dist: djangorestframework (~=3.13.1)
Requires-Dist: channels (~=3.0.4)
Provides-Extra: docs
Requires-Dist: sphinx ; extra == 'docs'
Requires-Dist: sphinx-rtd-theme ; extra == 'docs'
Provides-Extra: package
Requires-Dist: twine ; extra == 'package'
Requires-Dist: wheel ; extra == 'package'
Provides-Extra: test
Requires-Dist: django-filter (~=21.1) ; extra == 'test'
Requires-Dist: django-guardian (>=2.4.0) ; extra == 'test'
Requires-Dist: django-priority-batch (==4.*,>=4.0a1) ; extra == 'test'
Requires-Dist: channels-redis (~=3.3.1) ; extra == 'test'
Requires-Dist: pytest (>=7.0.1) ; extra == 'test'
Requires-Dist: pytest-django (>=3.5.2) ; extra == 'test'
Requires-Dist: pytest-asyncio (>=0.16.0) ; extra == 'test'
Requires-Dist: async-timeout (~=4.0.2) ; extra == 'test'
Requires-Dist: psycopg2-binary (~=2.9.3) ; extra == 'test'
Requires-Dist: check-manifest ; extra == 'test'
Requires-Dist: twine ; extra == 'test'
Requires-Dist: setuptools-scm ; extra == 'test'
Requires-Dist: black ; extra == 'test'
